bootstrapi/__init__.py
bootstrapi/conversion.py
bootstrapi/parser.py
bootstrapi/router.py
bootstrapi/sqlalchemy.py
bootstrapi-0.1.1.dist-info/LICENSE
bootstrapi-0.1.1.dist-info/METADATA
bootstrapi-0.1.1.dist-info/WHEEL
bootstrapi-0.1.1.dist-info/top_level.txt
bootstrapi-0.1.1.dist-info/RECORD
