Metadata-Version: 2.1
Name: bootstrapi
Version: 0.1.1
Summary: Generate an API from an existing database automatically. Includes OpenAPI docs and OData like queries.
Home-page: https://github.com/mrpowerus/bootstrAPI
Author: Mike Pieters
Author-email: me@mikepieters.com
License: UNKNOWN
Project-URL: Bug Tracker, https://github.com/mrpowerus/bootstrAPI/issues
Platform: UNKNOWN
Classifier: Programming Language :: Python :: 3
Classifier: License :: OSI Approved :: GNU General Public License v3 (GPLv3)
Classifier: Operating System :: OS Independent
Requires-Python: >=3.6
License-File: LICENSE
Requires-Dist: fastapi
Requires-Dist: SQLAlchemy
Requires-Dist: uvicorn
Requires-Dist: requests
